{"_ts":[1485908187,1485951494,1485995389],"_r":{"breakdown":{"html":{"bytes":[39675,40428,43274],"requests":[19,20,23]},"js":{"bytes":[963631,968030,963282],"requests":[53,54,53]},"css":{"bytes":[79415,79409,79421],"requests":[5,5,5]},"image":{"bytes":[1002174,1000781,1017668],"requests":[142,143,152]},"flash":{"bytes":[0,0,0],"requests":[0,0,0]},"font":{"bytes":[28996,29067,28996],"requests":[1,1,1]},"other":{"bytes":[9258,9258,8586],"requests":[5,5,3]}},"date":[1485908187,1485951494,1485995389],"domElements":[488,487.4,487],"domInteractive":[817.6,502.2,755.6],"firstPaint":[4840.6,3234.8,3751],"fullyLoaded":[21003.4,18434.4,19254.2],"id":["170201_6Z_733","170201_MQ_CGR0","170202_EB_B5S"],"loadTime":[10296.2,3990,6717.8],"render":[4623.6,3175,3579.2],"SpeedIndex":[5369.8,3659.4,4138.6],"TTFB":[630,359.2,433.2],"videoFrames":[[{"_t":0,"_vc":0},{"_t":4800,"_vc":2},{"_t":5600,"_vc":94},{"_t":6500,"_vc":96},{"_t":9400,"_vc":100}],[{"_t":0,"_vc":0},{"_t":3100,"_vc":1},{"_t":3500,"_vc":94},{"_t":4300,"_vc":96},{"_t":6700,"_vc":100}],[{"_t":0,"_vc":0},{"_t":4100,"_vc":2},{"_t":4200,"_vc":0},{"_t":4600,"_vc":94},{"_t":5700,"_vc":96},{"_t":7000,"_vc":100}]],"visualComplete":[8778.4,6337.2,7042.2]}}