{"_ts":[1481051408],"_r":{"breakdown":{"html":{"bytes":[102373],"requests":[18]},"js":{"bytes":[1500944],"requests":[63]},"css":{"bytes":[191029],"requests":[22]},"image":{"bytes":[1856927],"requests":[61]},"flash":{"bytes":[0],"requests":[0]},"font":{"bytes":[167203],"requests":[5]},"other":{"bytes":[6485],"requests":[9]}},"date":[1481051408],"domElements":[2650.2],"domInteractive":[3362.8],"firstPaint":[1780.4],"fullyLoaded":[15762],"id":["161206_9J_148M"],"loadTime":[8307.8],"render":[1965.8],"SpeedIndex":[4040.4],"TTFB":[520.6],"videoFrames":[[{"_t":0,"_vc":0},{"_t":1900,"_vc":16},{"_t":2100,"_vc":80},{"_t":2500,"_vc":80},{"_t":5500,"_vc":79},{"_t":6000,"_vc":79},{"_t":7800,"_vc":79},{"_t":8000,"_vc":1},{"_t":8800,"_vc":100}]],"visualComplete":[8598.6]}}